{
  "argument_id": "risk_control-f642a27ebc",
  "theme": "risk_control",
  "count": 1,
  "core": "EP675 | 🎢 突然想到上集有人許願要我放雲霄飛車我忘了 本集節目由【綠藤生機】贊助 每天早上 8:59 大盤都還沒開，各位情緒已經先開盤，手指放在下單鍵前先踩個煞車，你到底是照計畫走，還是被行情推著走？ 最該管理的不是部位，是自己。人到一個年紀乾淨感很重要，不要整個人看起來、聞起來，都像剛被大盤狠狠修理過。老朋友【綠藤生機】全系列 2 件 88 折，幫",
  "supporting_points": [
    "EP675 | 🎢 突然想到上集有人許願要我放雲霄飛車我忘了 本集節目由【綠藤生機】贊助 每天早上 8:59 大盤都還沒開，各位情緒已經先開盤，手指放在下單鍵前先踩個煞車，你到底是照計畫走，還是被行情推著走",
    "最該管理的不是部位，是自己",
    "人到一個年紀乾淨感很重要，不要整個人看起來、聞起來，都像剛被大盤狠狠修理過"
  ],
  "sources": [
    {
      "title": "EP675 | 🎢",
      "url": "https://player.soundon.fm/p/954689a5-3096-43a4-a80b-7810b219cef3/episodes/31e6121a-9d45-4204-aac1-f3a2cd7cd5fe",
      "published_at": "2026-07-01T15:59:09+08:00"
    }
  ]
}